.DS_Store
infrastructure/__init__.py
infrastructure/file_processing.py
infrastructure/base/__init__.py
infrastructure/base/con_mysql.py
infrastructure/base/dealTime.py
infrastructure/base/file_processing.py
infrastructure/base/file_processing2.py
infrastructure/base/network.py
infrastructure/base/parse_xlsx.py
infrastructure/base/save_rf_name.py
infrastructure/base/send_email.py
infrastructure/gitAbout/__init__.py
infrastructure/gitAbout/git_filter.py
infrastructure/gitAbout/git_operator.py
infrastructure/hb/__init__.py
infrastructure/hb/hb_request.py
infrastructure/hb/local_server.py
infrastructure/hb/operate_server.py
infrastructure/hb/serviceInfo.py
infrastructure/hb/third_interation.py
infrastructure/http_agent/__init__.py
infrastructure/http_agent/dingding.py
infrastructure/http_agent/http_request.py
infrastructure/parse/__init__.py
infrastructure/parse/htmlParse.py
infrastructure/parse/parse_xml.py
infrastructure/remoteServer/__init__.py
infrastructure/remoteServer/ssh_server.py
infrastructure/remoteServer/ssh_server2.py
infrastructure/rf/__init__.py
infrastructure/rf/testCaseFilters.py
infrastructure/variables/__init__.py
infrastructure/variables/hb_conf.py
infrastructure-3.5.6.dist-info/METADATA
infrastructure-3.5.6.dist-info/WHEEL
infrastructure-3.5.6.dist-info/top_level.txt
infrastructure-3.5.6.dist-info/RECORD
