Metadata-Version: 2.1
Name: infrastructure
Version: 3.5.6
Summary: test framework
Author: maoyongfan
Author-email: maoyongfan@163.com
License: MIT
Keywords: api test python language frameworks
Classifier: Development Status :: 3 - Alpha
Classifier: Intended Audience :: Developers
Classifier: Topic :: Software Development :: Build Tools
Classifier: License :: OSI Approved :: MIT License
Classifier: Programming Language :: Python :: 3
Classifier: Programming Language :: Python :: 3.7
Classifier: Operating System :: OS Independent
Requires-Python: >=3
Requires-Dist: paramiko (==2.7.1)
Requires-Dist: sshtunnel (==0.1.5)
